Metadata-Version: 1.1
Name: simplefc
Version: 1.1.3
Summary: A simple command-line flash card interface.
Home-page: https://github.com/vlahm/simplefc
Author: Mike Vlah
Author-email: vlahm13@gmail.com
License: GPL-3
Keywords: cli,desktop,tools,utility,study,memory,lifehacks,brain
Platform: UNKNOWN
Classifier: Intended Audience :: End Users/Desktop
Classifier: Topic :: Utilities
Classifier: License :: OSI Approved :: GNU General Public License v3 (GPLv3)
Classifier: Natural Language :: English
Classifier: Operating System :: OS Independent
Classifier: Programming Language :: Python :: 2
Classifier: Programming Language :: Python :: 2.7
Classifier: Programming Language :: Python :: 3
Classifier: Programming Language :: Python :: 3.5
